r2matte/__init__.py
r2matte/følger.py
r2matte/standardavik.py
r2matte-0.0.2.dist-info/METADATA
r2matte-0.0.2.dist-info/WHEEL
r2matte-0.0.2.dist-info/top_level.txt
r2matte-0.0.2.dist-info/RECORD
