Metadata-Version: 2.4
Name: r2matte
Version: 0.0.2
Summary: Verktøy for R2-matte: hjelper deg med å finne løsninger til oppgaver med bruk av AI
Author-email: André Hansen <Andre.Hansen146@gmail.com>
Requires-Python: >=3.9
